miniogl/AnchorPoint.py
miniogl/Common.py
miniogl/Constants.py
miniogl/ControlPoint.py
miniogl/Diagram.py
miniogl/DiagramFrame.py
miniogl/DlgDebugDiagramFrame.py
miniogl/LinePoint.py
miniogl/LineShape.py
miniogl/LollipopLine.py
miniogl/MiniOglColorEnum.py
miniogl/MiniOglPenStyle.py
miniogl/MiniOglUtils.py
miniogl/PointShape.py
miniogl/RectangleShape.py
miniogl/SelectAnchorPoint.py
miniogl/Shape.py
miniogl/ShapeEventHandler.py
miniogl/SizerShape.py
miniogl/TextShape.py
miniogl/__init__.py
miniogl/py.typed
miniogl/models/RectangleShapeModel.py
miniogl/models/ShapeModel.py
miniogl/models/TextShapeModel.py
miniogl/models/__init__.py
miniogl/models/py.typed
miniogl/rotatable/RotatableShape.py
miniogl/rotatable/VShapes.py
miniogl/rotatable/__init__.py
miniogl/rotatable/py.typed
ogl/EventEngineMixin.py
ogl/IllegalOperationException.py
ogl/OglActor.py
ogl/OglAggregation.py
ogl/OglAssociation.py
ogl/OglAssociationLabel.py
ogl/OglClass.py
ogl/OglComposition.py
ogl/OglConstants.py
ogl/OglDimensions.py
ogl/OglInheritance.py
ogl/OglInterface.py
ogl/OglInterface2.py
ogl/OglLink.py
ogl/OglLinkFactory.py
ogl/OglNote.py
ogl/OglNoteLink.py
ogl/OglObject.py
ogl/OglPosition.py
ogl/OglText.py
ogl/OglTextFontFamily.py
ogl/OglUseCase.py
ogl/OglUtils.py
ogl/__init__.py
ogl/_version.py
ogl/py.typed
ogl/events/IOglEventEngine.py
ogl/events/InvalidKeywordException.py
ogl/events/OglEventEngine.py
ogl/events/OglEvents.py
ogl/events/ShapeSelectedEventData.py
ogl/events/__init__.py
ogl/events/py.typed
ogl/preferences/OglPreferences.py
ogl/preferences/__init__.py
ogl/preferences/py.typed
ogl/resources/__init__.py
ogl/resources/img/Display.py
ogl/resources/img/DoNotDisplay.py
ogl/resources/img/UnSpecified.py
ogl/resources/img/__init__.py
ogl/resources/img/py.typed
ogl/resources/img/textdetails/DecreaseTextSize.py
ogl/resources/img/textdetails/IncreaseTextSize.py
ogl/resources/img/textdetails/__init__.py
ogl/resources/img/textdetails/py.typed
ogl/sd/OglInstanceName.py
ogl/sd/OglSDAnchorPoint.py
ogl-3.6.7.dist-info/LICENSE
ogl-3.6.7.dist-info/METADATA
ogl-3.6.7.dist-info/WHEEL
ogl-3.6.7.dist-info/top_level.txt
ogl-3.6.7.dist-info/RECORD
