Metadata-Version: 2.2
Name: ogl
Version: 3.6.7
Summary: External Pyut Graphical Shapes
Author-email: "Humberto A. Sanchez II" <Humbert.A.Sanchez.II@gmail.com>
Maintainer-email: "Humberto A. Sanchez II" <Humbert.A.Sanchez.II@gmail.com>
License: GNU AFFERO GENERAL PUBLIC LICENSE
Project-URL: Repository, https://github.com/hasii2011/ogl
Keywords: pyut,graphical shapes,python
Classifier: Programming Language :: Python
Classifier: Intended Audience :: Developers
Classifier: License :: OSI Approved :: GNU Affero General Public License v3
Classifier: Operating System :: MacOS :: MacOS X
Classifier: Topic :: Software Development :: Libraries :: Python Modules
License-File: LICENSE
Requires-Dist: wxPython~=4.2.2
Requires-Dist: codeallybasic>=1.9.0
Requires-Dist: codeallyadvanced>=1.3.3
Requires-Dist: pyutmodelv2>=2.2.3
Provides-Extra: test
Requires-Dist: mypy==1.14.0; extra == "test"
Requires-Dist: mypy-extensions==1.0.0; extra == "test"
Requires-Dist: types-Deprecated==1.2.9.20240311; extra == "test"
Requires-Dist: html-testRunner~=1.2.1; extra == "test"
Provides-Extra: deploy
Requires-Dist: wheel==0.45.1; extra == "deploy"
Requires-Dist: setuptools==75.7.0; extra == "deploy"
Requires-Dist: twine==6.0.1; extra == "deploy"
Requires-Dist: build==1.2.2.post1; extra == "deploy"
